odoo/addons/purchase_invoice_create_security_group/README.rst
odoo/addons/purchase_invoice_create_security_group/__init__.py
odoo/addons/purchase_invoice_create_security_group/__manifest__.py
odoo/addons/purchase_invoice_create_security_group/i18n/es.po
odoo/addons/purchase_invoice_create_security_group/i18n/it.po
odoo/addons/purchase_invoice_create_security_group/i18n/purchase_invoice_create_security_group.pot
odoo/addons/purchase_invoice_create_security_group/models/__init__.py
odoo/addons/purchase_invoice_create_security_group/models/purchase_order.py
odoo/addons/purchase_invoice_create_security_group/models/res_company.py
odoo/addons/purchase_invoice_create_security_group/models/res_config_settings.py
odoo/addons/purchase_invoice_create_security_group/readme/CONTRIBUTORS.rst
odoo/addons/purchase_invoice_create_security_group/readme/DESCRIPTION.rst
odoo/addons/purchase_invoice_create_security_group/readme/USAGE.rst
odoo/addons/purchase_invoice_create_security_group/security/security.xml
odoo/addons/purchase_invoice_create_security_group/static/description/icon.png
odoo/addons/purchase_invoice_create_security_group/static/description/index.html
odoo/addons/purchase_invoice_create_security_group/tests/__init__.py
odoo/addons/purchase_invoice_create_security_group/tests/test_invoice_group.py
odoo/addons/purchase_invoice_create_security_group/views/purchase_order.xml
odoo/addons/purchase_invoice_create_security_group/views/res_config_settings.xml
odoo14_addon_purchase_invoice_create_security_group-14.0.1.0.1.dev6.dist-info/METADATA
odoo14_addon_purchase_invoice_create_security_group-14.0.1.0.1.dev6.dist-info/WHEEL
odoo14_addon_purchase_invoice_create_security_group-14.0.1.0.1.dev6.dist-info/top_level.txt
odoo14_addon_purchase_invoice_create_security_group-14.0.1.0.1.dev6.dist-info/RECORD
